chalmers_qubit/__init__.py
chalmers_qubit/devices/__init__.py
chalmers_qubit/devices/sarimner/__init__.py
chalmers_qubit/devices/sarimner/compiler.py
chalmers_qubit/devices/sarimner/model.py
chalmers_qubit/devices/sarimner/noise.py
chalmers_qubit/devices/sarimner/processor.py
chalmers_qubit/utils/__init__.py
chalmers_qubit/utils/gates.py
chalmers_qubit/utils/operations.py
chalmers_qubit/utils/transformation.py
chalmers_qubit/utils/randomized_benchmarking/__init__.py
chalmers_qubit/utils/randomized_benchmarking/clifford_group.py
chalmers_qubit/utils/randomized_benchmarking/pauli_transfer_matrices.py
chalmers_qubit/utils/randomized_benchmarking/randomized_benchmarking.py
chalmers_qubit-2.1.3.dist-info/licenses/LICENSE
docs/scripts/gen_ref_pages.py
tests/__init__.py
tests/test_docs_build.py
tests/devices/__init__.py
tests/devices/sarimner/__init__.py
tests/devices/sarimner/test_compiler.py
tests/devices/sarimner/test_noise.py
tests/utils/__init__.py
tests/utils/test_operations.py
tests/utils/randomized_benchmarking/__init__.py
tests/utils/randomized_benchmarking/test_clifford_group.py
tests/utils/randomized_benchmarking/test_randomized_benchmarking.py
chalmers_qubit-2.1.3.dist-info/METADATA
chalmers_qubit-2.1.3.dist-info/WHEEL
chalmers_qubit-2.1.3.dist-info/top_level.txt
chalmers_qubit-2.1.3.dist-info/RECORD
