Metadata-Version: 2.4
Name: chalmers_qubit
Version: 2.1.3
Summary: A simulator of the Chalmers device to be used with qutip-qip
Author: Shahnawaz Ahmed
Author-email: Pontus Vikstål <vikstal@chalmers.se>
Maintainer-email: Pontus Vikstål <vikstal@chalmers.se>
Project-URL: Documentation, https://aqp-mc2-chalmers.github.io/chalmers-qubit/
Project-URL: Homepage, https://github.com/aqp-mc2-chalmers/chalmers-qubit
Project-URL: Repository, https://github.com/aqp-mc2-chalmers/chalmers-qubit.git
Keywords: superconducting qubits,pulse simulator,quantum computing
Classifier: Programming Language :: Python :: 3.10
Classifier: Operating System :: OS Independent
Classifier: License :: OSI Approved :: BSD License
Requires-Python: ~=3.10
License-File: LICENSE
Requires-Dist: qutip==5.1.1
Requires-Dist: qutip-qip==0.4.1
Requires-Dist: qutip-qtrl==0.1.5
Requires-Dist: matplotlib>=3.9.3
Provides-Extra: docs
Requires-Dist: mkdocs-material==9.6.14; extra == "docs"
Requires-Dist: mkdocstrings[python]~=0.29; extra == "docs"
Requires-Dist: mkdocs-gen-files==0.5.0; extra == "docs"
Requires-Dist: mkdocs-literate-nav==0.6.2; extra == "docs"
Requires-Dist: mkdocs-bibtex==4.2.10; extra == "docs"
Requires-Dist: mkdocs-jupyter==0.25.1; extra == "docs"
Requires-Dist: black==25.1.0; extra == "docs"
Dynamic: license-file
